idir2pdf/__init__.py
idir2pdf/idir2pdf.py
idir2pdf-0.1.3.dist-info/METADATA
idir2pdf-0.1.3.dist-info/WHEEL
idir2pdf-0.1.3.dist-info/entry_points.txt
idir2pdf-0.1.3.dist-info/licenses/LICENSE
idir2pdf-0.1.3.dist-info/RECORD
