Metadata-Version: 2.3
Name: idir2pdf
Version: 0.1.3
Summary: convert zip file including image to pdf file
Project-URL: Homepage, https://github.com/hy20191108/idir2pdf
Author-email: Yoshioka <zwwp9976@gmail.com>
License-File: LICENSE
Requires-Python: >=3.8
Requires-Dist: img2pdf>=0.5.1
Requires-Dist: natsort>=6.2.0
Requires-Dist: pillow-avif-plugin>=1.4.3
Requires-Dist: pillow-heif>=0.16.0
Requires-Dist: pillow>=10.3.0
Requires-Dist: tqdm>=4.66.4
